djallin2/OAuth2Receiver.py
djallin2/SoundServer.py
djallin2/StatTracker.py
djallin2/__init__.py
djallin2/__main__.py
djallin2/cli.py
djallin2/twitch.py
djallin2-0.8.2.dist-info/METADATA
djallin2-0.8.2.dist-info/WHEEL
djallin2-0.8.2.dist-info/top_level.txt
djallin2-0.8.2.dist-info/RECORD
