Metadata-Version: 2.1
Name: djallin2
Version: 0.8.2
Summary: Twitch noisemaker
Home-page: https://github.com/vilhelmen/djallin2
License: UNKNOWN
Platform: UNKNOWN
Classifier: Programming Language :: Python :: 3
Classifier: License :: OSI Approved :: MIT License
Classifier: Operating System :: MacOS
Classifier: Operating System :: Microsoft :: Windows
Requires-Python: >=3.9
Requires-Dist: toml
Requires-Dist: tomlkit
Requires-Dist: requests
Requires-Dist: python-dateutil
Requires-Dist: websockets
Requires-Dist: packaging
Requires-Dist: pyobjc ; platform_system == "Darwin"
Requires-Dist: pywin32 ; platform_system == "Windows"
